LICENSE
README.md
setup.py
docums_monorepo_plugin/__init__.py
docums_monorepo_plugin/merger.py
docums_monorepo_plugin/parser.py
docums_monorepo_plugin/plugin.py
docums_monorepo_plugin.egg-info/PKG-INFO
docums_monorepo_plugin.egg-info/SOURCES.txt
docums_monorepo_plugin.egg-info/dependency_links.txt
docums_monorepo_plugin.egg-info/entry_points.txt
docums_monorepo_plugin.egg-info/requires.txt
docums_monorepo_plugin.egg-info/top_level.txt