Metadata-Version: 2.1
Name: docums-monorepo-plugin
Version: 0.5.2
Summary: Plugin for adding monorepository support in Docums.
Home-page: https://github.com/khanhduy1407/docums-monorepo-plugin
Author: NKDuy
Author-email: kn145660@gmail.com
License: Apache-2.0
Keywords: docums monorepo
Platform: UNKNOWN
Classifier: Development Status :: 4 - Beta
Classifier: Intended Audience :: Developers
Classifier: Intended Audience :: Information Technology
Classifier: Programming Language :: Python
Classifier: Programming Language :: Python :: 3 :: Only
Classifier: Programming Language :: Python :: 3.6
Classifier: Programming Language :: Python :: 3.7
Requires-Python: >=3
License-File: LICENSE
